test/alu/tb_alu_2.v
`timescale 1ns/1ps

module tb_alu_2;
    // Test the ALU directly
    reg clk = 0;
    reg [31:0] reg_op1, reg_op2;
    reg instr_add, instr_sub, instr_and, instr_or, instr_xor;
    reg instr_sll, instr_srl, instr_sra;
    reg instr_slt, instr_sltu;
    reg instr_beq, instr_bne, instr_blt, instr_bge, instr_bltu, instr_bgeu;
    
    // Internal ALU signals (from the actual implementation)
    wire [31:0] alu_add_sub;
    wire [31:0] alu_shl, alu_shr;
    wire alu_eq, alu_ltu, alu_lts;
    
    wire alu_out_0;
    reg [31:0] alu_out;
    
    // Clock generation
    always #5 clk = ~clk;
    
    // Direct copy of ALU logic from picorv32
    assign alu_add_sub = instr_sub ? reg_op1 - reg_op2 : reg_op1 + reg_op2;
    assign alu_eq = reg_op1 == reg_op2;
    assign alu_lts = $signed(reg_op1) < $signed(reg_op2);
    assign alu_ltu = reg_op1 < reg_op2;
    assign alu_shl = reg_op1 << reg_op2[4:0];
    assign alu_shr = $signed({instr_sra ? reg_op1[31] : 1'b0, reg_op1}) >>> reg_op2[4:0];
    
    // ALU output multiplexing (from actual picorv32)
    assign alu_out_0 = 
        instr_beq ? alu_eq :
        instr_bne ? !alu_eq :
        instr_bge ? !alu_lts :
        instr_bgeu ? !alu_ltu :
        (instr_slt || instr_blt) ? alu_lts :
        (instr_sltu || instr_bltu) ? alu_ltu :
        1'bx;
    
    always @* begin
        alu_out = 'bx;
        if (instr_add || instr_sub) alu_out = alu_add_sub;
        else if (instr_xor) alu_out = reg_op1 ^ reg_op2;
        else if (instr_or) alu_out = reg_op1 | reg_op2;
        else if (instr_and) alu_out = reg_op1 & reg_op2;
        else if (instr_sll) alu_out = alu_shl;
        else if (instr_srl || instr_sra) alu_out = alu_shr;
        else if (instr_beq || instr_bne || instr_blt || instr_bge || instr_bltu || instr_bgeu || 
                 instr_slt || instr_sltu) alu_out = {31'b0, alu_out_0};
    end
    
    // Test sequence
    initial begin
        // Create VCD file for this testbench
        $dumpfile("waves_alu.vcd");
        $dumpvars(0, tb_alu_2);
        
        $display("=== ALU UNIT TEST (PicoRV32 Style) ===");
        
        // Initialize
        reg_op1 = 0;
        reg_op2 = 0;
        instr_add = 0; instr_sub = 0; instr_and = 0; instr_or = 0; instr_xor = 0;
        instr_sll = 0; instr_srl = 0; instr_sra = 0;
        instr_slt = 0; instr_sltu = 0;
        instr_beq = 0; instr_bne = 0; instr_blt = 0; instr_bge = 0; instr_bltu = 0; instr_bgeu = 0;
        
        #10;  // Wait a clock cycle
        
        // Test 1: ADD
        @(posedge clk);
        reg_op1 = 32'h00000005;
        reg_op2 = 32'h00000003;
        instr_add = 1;
        @(posedge clk);
        $display("[%0t] ADD: %h + %h = %h (expected: 8)", 
                 $time, reg_op1, reg_op2, alu_out);
        if (alu_out !== 32'h00000008) $error("ADD failed!");
        instr_add = 0;
        
        // Test 2: SUB
        @(posedge clk);
        instr_sub = 1;
        @(posedge clk);
        $display("[%0t] SUB: %h - %h = %h (expected: 2)", 
                 $time, reg_op1, reg_op2, alu_out);
        if (alu_out !== 32'h00000002) $error("SUB failed!");
        instr_sub = 0;
        
        // Test 3: AND
        @(posedge clk);
        reg_op1 = 32'hF0F0F0F0;
        reg_op2 = 32'h0F0F0F0F;
        instr_and = 1;
        @(posedge clk);
        $display("[%0t] AND: %h & %h = %h (expected: 0)", 
                 $time, reg_op1, reg_op2, alu_out);
        if (alu_out !== 32'h00000000) $error("AND failed!");
        instr_and = 0;
        
        // Test 4: OR
        @(posedge clk);
        instr_or = 1;
        @(posedge clk);
        $display("[%0t] OR: %h | %h = %h (expected: FFFFFFFF)", 
                 $time, reg_op1, reg_op2, alu_out);
        if (alu_out !== 32'hFFFFFFFF) $error("OR failed!");
        instr_or = 0;
        
        // Test 5: XOR
        @(posedge clk);
        instr_xor = 1;
        @(posedge clk);
        $display("[%0t] XOR: %h ^ %h = %h (expected: FFFFFFFF)", 
                 $time, reg_op1, reg_op2, alu_out);
        if (alu_out !== 32'hFFFFFFFF) $error("XOR failed!");
        instr_xor = 0;
        
        // Test 6: Shift Left
        @(posedge clk);
        reg_op1 = 32'h00000001;
        reg_op2 = 32'h00000004;
        instr_sll = 1;
        @(posedge clk);
        $display("[%0t] SLL: %h << %h = %h (expected: 10)", 
                 $time, reg_op1, reg_op2, alu_out);
        if (alu_out !== 32'h00000010) $error("SLL failed!");
        instr_sll = 0;
        
        // Test 7: Shift Right Logical
        @(posedge clk);
        reg_op1 = 32'hF0000000;
        reg_op2 = 32'h00000004;
        instr_srl = 1;
        @(posedge clk);
        $display("[%0t] SRL: %h >> %h = %h (expected: 0F000000)", 
                 $time, reg_op1, reg_op2, alu_out);
        if (alu_out !== 32'h0F000000) $error("SRL failed!");
        instr_srl = 0;

        // Test 8: Shift Right Arithmetic (SRA - negative)
        @(posedge clk);
        reg_op1 = 32'hF0000000; // negative number
        reg_op2 = 32'h00000004;
        instr_sra = 1;
        @(posedge clk);
        $display("[%0t] SRA (neg): %h >>> %h = %h (expected: FF000000)", 
                $time, reg_op1, reg_op2, alu_out);
        if (alu_out !== 32'hFF000000) $error("SRA failed on negative number!"); 
        instr_sra = 0;

        // Test 9: Shift Right Arithmetic (SRA - positive)
        @(posedge clk);
        reg_op1 = 32'h70000000; // positive number
        reg_op2 = 32'h00000004;
        instr_sra = 1;
        @(posedge clk);
        $display("[%0t] SRA (pos): %h >>> %h = %h (expected: 07000000)", 
                $time, reg_op1, reg_op2, alu_out);
        if (alu_out !== 32'h07000000) $error("SRA failed on positive number!");
        instr_sra = 0;
        
        // Test 10: Compare operations
        @(posedge clk);
        reg_op1 = 32'h00000005;
        reg_op2 = 32'h00000003;
        
        // Test 10a: SLT (signed less than) - false
        instr_slt = 1;
        @(posedge clk);
        $display("[%0t] SLT: %h <s %h = %h (expected: 0)", 
                 $time, reg_op1, reg_op2, alu_out);
        if (alu_out !== 32'h00000000) $error("SLT failed!");
        instr_slt = 0;
        
        // Test 10b: SLTU (unsigned less than) - false
        instr_sltu = 1;
        @(posedge clk);
        $display("[%0t] SLTU: %h <u %h = %h (expected: 0)", 
                 $time, reg_op1, reg_op2, alu_out);
        if (alu_out !== 32'h00000000) $error("SLTU failed!");
        instr_sltu = 0;
        
        // Test 10c: BLT (branch if less than) - false
        instr_blt = 1;
        @(posedge clk);
        $display("[%0t] BLT: %h <s %h = %h (expected: 0)", 
                 $time, reg_op1, reg_op2, alu_out);
        if (alu_out !== 32'h00000000) $error("BLT failed!");
        instr_blt = 0;
        
        // Test 10d: BLTU (branch if less than unsigned) - false
        instr_bltu = 1;
        @(posedge clk);
        $display("[%0t] BLTU: %h <u %h = %h (expected: 0)", 
                 $time, reg_op1, reg_op2, alu_out);
        if (alu_out !== 32'h00000000) $error("BLTU failed!");
        instr_bltu = 0;
        
        // Test 11: Compare with negative numbers
        @(posedge clk);
        reg_op1 = 32'hFFFFFFFF; // -1 signed, 4294967295 unsigned
        reg_op2 = 32'h00000001; // +1
        
        // Test 11a: SLT (-1 < 1) - true
        instr_slt = 1;
        @(posedge clk);
        $display("[%0t] SLT: %h <s %h = %h (expected: 1)", 
                 $time, reg_op1, reg_op2, alu_out);
        if (alu_out !== 32'h00000001) $error("SLT with negative failed!");
        instr_slt = 0;
        
        // Test 11b: SLTU (4294967295 < 1) - false
        instr_sltu = 1;
        @(posedge clk);
        $display("[%0t] SLTU: %h <u %h = %h (expected: 0)", 
                 $time, reg_op1, reg_op2, alu_out);
        if (alu_out !== 32'h00000000) $error("SLTU with negative failed!");
        instr_sltu = 0;
        
        // Test 12: Equality comparisons
        @(posedge clk);
        reg_op1 = 32'h12345678;
        reg_op2 = 32'h12345678;
        
        // Test 12a: BEQ (branch if equal) - true
        instr_beq = 1;
        @(posedge clk);
        $display("[%0t] BEQ: %h == %h = %h (expected: 1)", 
                 $time, reg_op1, reg_op2, alu_out);
        if (alu_out !== 32'h00000001) $error("BEQ failed!");
        instr_beq = 0;
        
        // Test 12b: BNE (branch if not equal) - false
        instr_bne = 1;
        @(posedge clk);
        $display("[%0t] BNE: %h != %h = %h (expected: 0)", 
                 $time, reg_op1, reg_op2, alu_out);
        if (alu_out !== 32'h00000000) $error("BNE failed!");
        instr_bne = 0;
        
        // Test 13: Edge cases
        @(posedge clk);
        reg_op1 = 32'h80000000; // Most negative signed number
        reg_op2 = 32'h00000001;
        
        // Test 13a: BGE (branch if greater or equal) - false
        instr_bge = 1;
        @(posedge clk);
        $display("[%0t] BGE: %h >=s %h = %h (expected: 0)", 
                 $time, reg_op1, reg_op2, alu_out);
        if (alu_out !== 32'h00000000) $error("BGE with min negative failed!");
        instr_bge = 0;
        
        // Test 13b: BGEU (branch if greater or equal unsigned) - true
        instr_bgeu = 1;
        @(posedge clk);
        $display("[%0t] BGEU: %h >=u %h = %h (expected: 1)", 
                 $time, reg_op1, reg_op2, alu_out);
        if (alu_out !== 32'h00000001) $error("BGEU with min negative failed!");
        instr_bgeu = 0;

        #20;
        $display("=================================");
        $display("ALU tests completed successfully!");
        $display("=================================");
        $finish;
    end
endmodule

ongo/alu/waves_alu.vcd
$date
	Thu Jan 29 14:14:13 2026
$end
$version
	Icarus Verilog
$end
$timescale
	1ps
$end
$scope module tb_alu_2 $end
$var wire 32 ! alu_shr [31:0] $end
$var wire 32 " alu_shl [31:0] $end
$var wire 1 # alu_out_0 $end
$var wire 1 $ alu_ltu $end
$var wire 1 % alu_lts $end
$var wire 1 & alu_eq $end
$var wire 32 ' alu_add_sub [31:0] $end
$var reg 32 ( alu_out [31:0] $end
$var reg 1 ) clk $end
$var reg 1 * instr_add $end
$var reg 1 + instr_and $end
$var reg 1 , instr_beq $end
$var reg 1 - instr_bge $end
$var reg 1 . instr_bgeu $end
$var reg 1 / instr_blt $end
$var reg 1 0 instr_bltu $end
$var reg 1 1 instr_bne $end
$var reg 1 2 instr_or $end
$var reg 1 3 instr_sll $end
$var reg 1 4 instr_slt $end
$var reg 1 5 instr_sltu $end
$var reg 1 6 instr_sra $end
$var reg 1 7 instr_srl $end
$var reg 1 8 instr_sub $end
$var reg 1 9 instr_xor $end
$var reg 32 : reg_op1 [31:0] $end
$var reg 32 ; reg_op2 [31:0] $end
$upscope $end
$enddefinitions $end
$comment Show the parameter values. $end
$dumpall
$end
#0
$dumpvars
b0 ;
b0 :
09
08
07
06
05
04
03
02
01
00
0/
0.
0-
0,
0+
0*
0)
bx (
b0 '
1&
0%
0$
x#
b0 "
b0 !
$end
#5000
1)
#10000
0)
#15000
b1000 '
b1000 (
b0 !
1*
b11 ;
0&
b101000 "
b101 :
1)
#20000
0)
#25000
bx (
0*
1)
#30000
0)
#35000
b10 (
b10 '
18
1)
#40000
0)
#45000
bx (
b1000 '
08
1)
#50000
0)
#55000
b11111111111111111111111111111111 '
b0 (
b11110000111100001 !
1+
b1111000011110000111100001111 ;
1%
b1111000011110000000000000000000 "
b11110000111100001111000011110000 :
1)
#60000
0)
#65000
bx (
0+
1)
#70000
0)
#75000
b11111111111111111111111111111111 (
12
1)
#80000
0)
#85000
bx (
02
1)
#90000
0)
#95000
b11111111111111111111111111111111 (
19
1)
#100000
0)
#105000
bx (
09
1)
#110000
0)
#115000
b101 '
b10000 (
b0 !
13
b100 ;
1$
b10000 "
b1 :
1)
#120000
0)
#125000
bx (
03
1)
#130000
0)
#135000
b11110000000000000000000000000100 '
b1111000000000000000000000000 (
b1111000000000000000000000000 !
17
0$
b0 "
b11110000000000000000000000000000 :
1)
#140000
0)
#145000
bx (
07
1)
#150000
0)
#155000
b11111111000000000000000000000000 !
b11111111000000000000000000000000 (
16
1)
#160000
0)
#165000
b1111000000000000000000000000 !
bx (
06
1)
#170000
0)
#175000
b111000000000000000000000000 (
b1110000000000000000000000000100 '
b111000000000000000000000000 !
16
0%
b1110000000000000000000000000000 :
1)
#180000
0)
#185000
bx (
06
1)
#190000
0)
#195000
0#
b1000 '
b0 (
b0 !
14
b11 ;
b101000 "
b101 :
1)
#200000
0)
#205000
0#
b0 (
15
04
1)
#210000
0)
#215000
b0 (
1/
05
1)
#220000
0)
#225000
0#
b0 (
10
0/
1)
#230000
0)
#235000
x#
bx (
00
1)
#240000
0)
#245000
1#
b0 '
b1 (
b1111111111111111111111111111111 !
14
b1 ;
1%
b11111111111111111111111111111110 "
b11111111111111111111111111111111 :
1)
#250000
0)
#255000
0#
b0 (
15
04
1)
#260000
0)
#265000
x#
bx (
05
1)
#270000
0)
#275000
1#
b100100011010001010110011110000 '
b1 (
b10010 !
1,
1&
b10010001101000101011001111000 ;
0%
b1111000000000000000000000000000 "
b10010001101000101011001111000 :
1)
#280000
0)
#285000
b0 (
0#
11
0,
1)
#290000
0)
#295000
x#
bx (
01
1)
#300000
0)
#305000
0#
b10000000000000000000000000000001 '
b0 (
b1000000000000000000000000000000 !
1-
b1 ;
0&
1%
b0 "
b10000000000000000000000000000000 :
1)
#310000
0)
#315000
1#
b1 (
1.
0-
1)
#320000
0)
#325000
x#
bx (
0.
1)
